h2o/__init__.py
h2o/assembly.py
h2o/astfun.py
h2o/auth.py
h2o/base.py
h2o/buildinfo.txt
h2o/cross_validation.py
h2o/debug.py
h2o/demos.py
h2o/display.py
h2o/exceptions.py
h2o/expr.py
h2o/expr_optimizer.py
h2o/frame.py
h2o/group_by.py
h2o/h2o.py
h2o/job.py
h2o/scoring.py
h2o/two_dim_table.py
h2o/version.txt
h2o/automl/__init__.py
h2o/automl/_base.py
h2o/automl/_estimator.py
h2o/automl/_output.py
h2o/automl/autoh2o.py
h2o/backend/__init__.py
h2o/backend/cluster.py
h2o/backend/connection.py
h2o/backend/server.py
h2o/backend/bin/h2o.jar
h2o/estimators/__init__.py
h2o/estimators/adaboost.py
h2o/estimators/aggregator.py
h2o/estimators/anovaglm.py
h2o/estimators/coxph.py
h2o/estimators/decision_tree.py
h2o/estimators/deeplearning.py
h2o/estimators/estimator_base.py
h2o/estimators/extended_isolation_forest.py
h2o/estimators/gam.py
h2o/estimators/gbm.py
h2o/estimators/generic.py
h2o/estimators/glm.py
h2o/estimators/glrm.py
h2o/estimators/hglm.py
h2o/estimators/infogram.py
h2o/estimators/isolation_forest.py
h2o/estimators/isotonicregression.py
h2o/estimators/kmeans.py
h2o/estimators/model_selection.py
h2o/estimators/naive_bayes.py
h2o/estimators/pca.py
h2o/estimators/psvm.py
h2o/estimators/random_forest.py
h2o/estimators/rulefit.py
h2o/estimators/sdt.py
h2o/estimators/single_decision_tree.py
h2o/estimators/stackedensemble.py
h2o/estimators/svd.py
h2o/estimators/targetencoder.py
h2o/estimators/uplift_random_forest.py
h2o/estimators/word2vec.py
h2o/estimators/xgboost.py
h2o/explanation/__init__.py
h2o/explanation/_explain.py
h2o/grid/__init__.py
h2o/grid/grid_search.py
h2o/grid/metrics.py
h2o/h2o_data/iris.csv
h2o/h2o_data/prostate.csv
h2o/information_retrieval/__init__.py
h2o/information_retrieval/tf_idf.py
h2o/model/__init__.py
h2o/model/confusion_matrix.py
h2o/model/metrics_base.py
h2o/model/model_base.py
h2o/model/model_builder.py
h2o/model/model_future.py
h2o/model/segment_models.py
h2o/model/extensions/__init__.py
h2o/model/extensions/contributions.py
h2o-3.46.0.8.dist-info/METADATA
h2o-3.46.0.8.dist-info/WHEEL
h2o-3.46.0.8.dist-info/top_level.txt
h2o-3.46.0.8.dist-info/RECORD
