Metadata-Version: 2.1
Name: h2o
Version: 3.46.0.8
Summary: H2O, Fast Scalable Machine Learning, for python 
Home-page: https://github.com/h2oai/h2o-3.git
Author: H2O.ai
Author-email: support@h2o.ai
License: Apache v2
Keywords: machine learning,data mining,statistical analysis,modeling,big data,distributed,parallel
Classifier: Development Status :: 5 - Production/Stable
Classifier: Intended Audience :: Education
Classifier: Intended Audience :: Developers
Classifier: Intended Audience :: Science/Research
Classifier: Intended Audience :: Customer Service
Classifier: Intended Audience :: Financial and Insurance Industry
Classifier: Intended Audience :: Healthcare Industry
Classifier: Intended Audience :: Telecommunications Industry
Classifier: Topic :: Scientific/Engineering :: Artificial Intelligence
Classifier: Topic :: Scientific/Engineering :: Information Analysis
Classifier: License :: OSI Approved :: Apache Software License
Classifier: Programming Language :: Python :: 3.6
Classifier: Programming Language :: Python :: 3.7
Classifier: Programming Language :: Python :: 3.8
Classifier: Programming Language :: Python :: 3.9
Classifier: Programming Language :: Python :: 3.10
Classifier: Programming Language :: Python :: 3.11
Requires-Dist: requests
Requires-Dist: tabulate
Provides-Extra: kerberos
Requires-Dist: gssapi ; extra == 'kerberos'
Requires-Dist: pykerberos <2.0.0,>=1.1.8 ; (sys_platform != "win32") and extra == 'kerberos'
Requires-Dist: winkerberos >=0.5.0 ; (sys_platform == "win32") and extra == 'kerberos'
